aioworkers_redis/__init__.py
aioworkers_redis/base.py
aioworkers_redis/queue.py
aioworkers_redis/storage.py
aioworkers_redis/version.py
aioworkers_redis-0.8.dist-info/LICENSE
aioworkers_redis-0.8.dist-info/METADATA
aioworkers_redis-0.8.dist-info/WHEEL
aioworkers_redis-0.8.dist-info/top_level.txt
aioworkers_redis-0.8.dist-info/RECORD
