Metadata-Version: 2.1
Name: aioworkers-redis
Version: 0.8
Summary: Module for working with redis
Home-page: https://github.com/aioworkers/aioworkers-redis
Author: Alexander Malev
Author-email: yttrium@somedev.ru
License: Apache Software License 2.0
Keywords: aioworkers redis
Platform: UNKNOWN
Classifier: Development Status :: 2 - Pre-Alpha
Classifier: Intended Audience :: Developers
Classifier: License :: OSI Approved :: Apache Software License
Classifier: Programming Language :: Python :: 3
Classifier: Programming Language :: Python :: 3.6
Classifier: Programming Language :: Python :: 3.7
Requires-Python: >=3.6
Requires-Dist: aioworkers (>=0.14.3)
Requires-Dist: aioredis (>=1.3.0)
